Metadata-Version: 1.0
Name: webwrite
Version: 0.0
Summary: You can make CSS and html bu this library
Home-page: UNKNOWN
Author: UNKNOWN
Author-email: dlyasevich@yandex.ru
License: UNKNOWN
Platform: UNKNOWN
